automaton/__init__.py
automaton/_utils.py
automaton/exceptions.py
automaton/machines.py
automaton/runners.py
automaton/converters/__init__.py
automaton/converters/pydot.py
automaton/tests/__init__.py
automaton/tests/test_fsm.py
automaton-3.2.0.dist-info/AUTHORS
automaton-3.2.0.dist-info/LICENSE
automaton-3.2.0.dist-info/METADATA
automaton-3.2.0.dist-info/WHEEL
automaton-3.2.0.dist-info/pbr.json
automaton-3.2.0.dist-info/top_level.txt
automaton-3.2.0.dist-info/RECORD
